cloudsql/__init__.py
cloudsql/auth.py
cloudsql/core.py
cloudsql/sqlite.py
cloudsql/utilities.py
cloudsql/views.py
cloudsql-0.1.0.dist-info/LICENSE
cloudsql-0.1.0.dist-info/METADATA
cloudsql-0.1.0.dist-info/WHEEL
cloudsql-0.1.0.dist-info/top_level.txt
cloudsql-0.1.0.dist-info/RECORD
