Metadata-Version: 2.1
Name: cloudsql
Version: 0.1.0
Summary: An SQL-to-REST library for python
Home-page: UNKNOWN
Author: Andreas Muetter
License: UNKNOWN
Platform: UNKNOWN
Classifier: Programming Language :: Python :: 3
Classifier: License :: OSI Approved :: MIT License
Classifier: Operating System :: OS Independent
Requires-Python: >=3.6
Requires-Dist: flask
